tamu_id_minter/__init__.py
tamu_id_minter/crossref/__init__.py
tamu_id_minter/crossref/crossref.py
tamu_id_minter/crossref/templates.py
tamu_id_minter/ezid/__init__.py
tamu_id_minter/ezid/ezid.py
tamu_id_minter/mint.py
tamu_id_minter-0.2.0.dist-info/METADATA
tamu_id_minter-0.2.0.dist-info/WHEEL
tamu_id_minter-0.2.0.dist-info/entry_points.txt
tamu_id_minter-0.2.0.dist-info/RECORD
