Metadata-Version: 2.1
Name: tamu-id-minter
Version: 0.2.0
Summary: 
Author: Mark Baggett
Author-email: markpbaggett@gmail.com
Requires-Python: >=3.12,<4.0
Classifier: Programming Language :: Python :: 3
Classifier: Programming Language :: Python :: 3.12
Requires-Dist: click (>=8.2.1,<9.0.0)
Requires-Dist: requests (>=2.32.5,<3.0.0)
Requires-Dist: tqdm (>=4.67.1,<5.0.0)
